weirdbase/__init__.py
weirdbase-0.1.1.dist-info/LICENSE
weirdbase-0.1.1.dist-info/WHEEL
weirdbase-0.1.1.dist-info/METADATA
weirdbase-0.1.1.dist-info/RECORD
