Metadata-Version: 2.1
Name: weirdbase
Version: 0.1.1
Summary: Converts integers to strange number bases using customizable base definitions
Author-email: Darren Meyer <darren@darrenpmeyer.com>
Classifier: License :: OSI Approved :: MIT License
Project-URL: Home, https://github.com/darrenpmeyer/python-weirdbase
